snappy/__init__.py
snappy/crawlers.py
snappy/tools.py
swift_snappy-0.0.1.dist-info/METADATA
swift_snappy-0.0.1.dist-info/WHEEL
swift_snappy-0.0.1.dist-info/top_level.txt
swift_snappy-0.0.1.dist-info/RECORD
